{
  "event_id": "019cfc28-a041-7291-8dd6-065e5cdf3a72",
  "occurred_at": "2026-03-17T14:17:26.842709Z",
  "type": "idx.knot_head",
  "data": {
    "deferred_from_state": null,
    "gate": {
      "owner_kind": "agent"
    },
    "invariants": [],
    "knot_id": "foolery-62fa",
    "profile_id": "autopilot_no_planning",
    "state": "implementation_review",
    "terminal": false,
    "title": "Queues:  You should be able to set state to Shipped, Abandon or Deferred during multi-select",
    "type": "work",
    "updated_at": "2026-03-17T14:17:26.842709Z"
  }
}
