{
  "event_id": "019cfc21-2a22-7040-9186-83bc9877139d",
  "occurred_at": "2026-03-17T14:09:17.858956Z",
  "type": "idx.knot_head",
  "data": {
    "deferred_from_state": null,
    "gate": {
      "owner_kind": "agent"
    },
    "invariants": [],
    "knot_id": "foolery-7171",
    "profile_id": "autopilot",
    "state": "ready_for_planning",
    "terminal": false,
    "title": "search should be a minimum view of 20 characters",
    "type": "work",
    "updated_at": "2026-03-17T14:09:17.858956Z"
  }
}
