{
  "event_id": "019df2ed-0c96-7330-934b-a422518f3c1f",
  "occurred_at": "2026-05-04T12:18:34.774764Z",
  "knot_id": "foolery-4f8e",
  "type": "knot.note_added",
  "data": {
    "agentname": "unknown",
    "content": "Shipment review approved. main and origin/main both point at a8ce5d74c65b26e29a2d74b565634a2555926f51. The implementation commit and branch tags are present on the knot. Remote GitHub checks for that commit are completed successfully: CI 25318430546 and Coverage Badge 25318430552. Shipped code preserves the single-source version contract and no dependent-system regression was found.",
    "datetime": "2026-05-04T12:18:34.774764Z",
    "entry_id": "019df2ed-0c96-7330-934b-a41e6550ede8",
    "model": "unknown",
    "username": "unknown",
    "version": "unknown"
  }
}
