{
  "event_id": "019d432e-120e-7550-ab13-bf52c14d8659",
  "occurred_at": "2026-03-31T09:16:25.998136Z",
  "type": "idx.knot_head",
  "data": {
    "blocked_from_state": null,
    "deferred_from_state": null,
    "gate": {
      "owner_kind": "agent"
    },
    "invariants": [],
    "knot_id": "foolery-b45e",
    "profile_id": "autopilot",
    "state": "shipment",
    "terminal": false,
    "title": "History Screen Shows Incorrect Agent for Logged Model",
    "type": "work",
    "updated_at": "2026-03-31T09:16:25.998136Z",
    "workflow_id": "compatibility"
  },
  "precondition": {
    "profile_etag": "019d432d-e730-7871-a0cd-ec75ed6c0461"
  }
}
