{
  "event_id": "019d4482-96da-79c0-be81-c8b1a6e3c854",
  "occurred_at": "2026-03-31T15:28:22.234729Z",
  "type": "idx.knot_head",
  "data": {
    "blocked_from_state": null,
    "deferred_from_state": null,
    "gate": {
      "owner_kind": "agent"
    },
    "invariants": [],
    "knot_id": "foolery-3037",
    "profile_id": "autopilot",
    "state": "lease_terminated",
    "terminal": true,
    "title": "Lease: foolery:terminal_manager_take:term-1774969430476-kvefax",
    "type": "lease",
    "updated_at": "2026-03-31T15:28:22.234729Z",
    "workflow_id": "compatibility"
  }
}
