{
  "event_id": "019d4470-1610-7303-8ac4-43a4baa39688",
  "occurred_at": "2026-03-31T15:08:09.616429Z",
  "type": "idx.knot_head",
  "data": {
    "blocked_from_state": null,
    "deferred_from_state": null,
    "gate": {
      "owner_kind": "agent"
    },
    "invariants": [],
    "knot_id": "foolery-eff0",
    "profile_id": "autopilot",
    "state": "lease_terminated",
    "terminal": true,
    "title": "Lease: foolery:terminal_manager_take:term-1774969430476-kvefax",
    "type": "lease",
    "updated_at": "2026-03-31T15:08:09.616429Z",
    "workflow_id": "compatibility"
  }
}
