{
  "event_id": "019d43e6-2e59-7e02-a10b-0b935c5c3dd6",
  "occurred_at": "2026-03-31T12:37:31.865864Z",
  "type": "idx.knot_head",
  "data": {
    "blocked_from_state": null,
    "deferred_from_state": null,
    "gate": {
      "owner_kind": "agent"
    },
    "invariants": [],
    "knot_id": "foolery-d480",
    "profile_id": "autopilot",
    "state": "lease_terminated",
    "terminal": true,
    "title": "Lease: foolery:terminal_manager_take:term-1774960645475-mygu03",
    "type": "lease",
    "updated_at": "2026-03-31T12:37:31.865864Z",
    "workflow_id": "compatibility"
  }
}
