{
  "event_id": "019d4321-a3b0-7ac2-a075-52f1e83d3c5c",
  "occurred_at": "2026-03-31T09:02:51.312104Z",
  "type": "idx.knot_head",
  "data": {
    "blocked_from_state": null,
    "deferred_from_state": null,
    "gate": {
      "owner_kind": "agent"
    },
    "invariants": [],
    "knot_id": "foolery-7e45",
    "profile_id": "autopilot",
    "state": "lease_ready",
    "terminal": false,
    "title": "Lease: foolery:terminal_manager_take:term-1774947060126-sloqn7",
    "type": "lease",
    "updated_at": "2026-03-31T09:02:51.312104Z",
    "workflow_id": "compatibility"
  }
}
