{
  "event_id": "019d4419-dcb9-7291-af5b-64ef363213c0",
  "occurred_at": "2026-03-31T13:33:58.841742Z",
  "type": "idx.knot_head",
  "data": {
    "blocked_from_state": null,
    "deferred_from_state": null,
    "gate": {
      "owner_kind": "agent"
    },
    "invariants": [],
    "knot_id": "foolery-15c4",
    "profile_id": "autopilot",
    "state": "lease_terminated",
    "terminal": true,
    "title": "Lease: foolery:terminal_manager_take:term-1774960645475-mygu03",
    "type": "lease",
    "updated_at": "2026-03-31T13:33:58.841742Z",
    "workflow_id": "compatibility"
  }
}
