{
  "event_id": "019d431a-57c5-7112-bfe8-376e210ac210",
  "occurred_at": "2026-03-31T08:54:53.125188Z",
  "type": "idx.knot_head",
  "data": {
    "blocked_from_state": null,
    "deferred_from_state": null,
    "gate": {
      "owner_kind": "agent"
    },
    "invariants": [],
    "knot_id": "foolery-b01f",
    "profile_id": "autopilot",
    "state": "lease_active",
    "terminal": false,
    "title": "Lease: foolery:terminal_manager_take:term-1774947076062-0xpvoc",
    "type": "lease",
    "updated_at": "2026-03-31T08:54:53.125188Z",
    "workflow_id": "compatibility"
  }
}
