{
  "event_id": "019d8ac7-28f6-7d73-9f96-c0afe44ad63a",
  "occurred_at": "2026-04-14T06:56:41.206043Z",
  "type": "idx.knot_head",
  "data": {
    "blocked_from_state": null,
    "deferred_from_state": null,
    "gate": {
      "owner_kind": "agent"
    },
    "invariants": [],
    "knot_id": "foolery-ca9a",
    "next_step_metadata": {
      "action_kind": "gate",
      "action_state": "plan_review",
      "output": {
        "artifact_type": "remote_main"
      },
      "owner": {
        "agent_model": null,
        "agent_name": null,
        "agent_version": null,
        "kind": "agent"
      }
    },
    "profile_id": "autopilot",
    "state": "ready_for_plan_review",
    "step_metadata": {
      "action_kind": "gate",
      "action_state": "plan_review",
      "output": {
        "artifact_type": "remote_main"
      },
      "owner": {
        "agent_model": null,
        "agent_name": null,
        "agent_version": null,
        "kind": "agent"
      }
    },
    "terminal": false,
    "title": "Drive Foolery plan steps from execution_plan payload",
    "type": "work",
    "updated_at": "2026-04-14T06:56:41.206043Z",
    "workflow_id": "work_sdlc"
  }
}
