{
  "event_id": "019e8c0c-2f78-7f21-ace1-8f1849383144",
  "occurred_at": "2026-06-03T05:54:29.368220271Z",
  "knot_id": "foolery-9cbd",
  "type": "knot.lease_data_set",
  "data": {
    "lease_data": {
      "agent_info": {
        "agent_name": "Codex",
        "agent_type": "cli",
        "model": "GPT Mini",
        "model_version": "5.4",
        "provider": "Codex"
      },
      "lease_type": "agent",
      "nickname": "foolery:terminal_manager_take:term-1780464499893-qrjf0i",
      "timeout_seconds": 600
    }
  }
}
