{
  "event_id": "019ceceb-0840-79a0-a183-06146a118d36",
  "occurred_at": "2026-03-14T15:15:51.994717Z",
  "type": "idx.knot_head",
  "data": {
    "deferred_from_state": null,
    "gate": {
      "owner_kind": "agent"
    },
    "invariants": [],
    "knot_id": "foolery-2ac4",
    "profile_id": "autopilot_with_pr",
    "state": "implementation",
    "terminal": false,
    "title": "expand rollbackBeatState unit tests in memory-manager-commands-coverage",
    "type": "work",
    "updated_at": "2026-03-14T15:15:51.994717Z"
  }
}
