{
  "event_id": "019ced12-21e7-75f3-9d53-a909e1d728de",
  "occurred_at": "2026-03-14T15:58:34.471538Z",
  "type": "idx.knot_head",
  "data": {
    "deferred_from_state": null,
    "gate": {
      "owner_kind": "agent"
    },
    "invariants": [],
    "knot_id": "foolery-742c",
    "profile_id": "autopilot_no_planning",
    "state": "implementation_review",
    "terminal": false,
    "title": "Create HistoryDebugPanel component with form and embedded terminal",
    "type": "work",
    "updated_at": "2026-03-14T15:58:34.471538Z"
  },
  "precondition": {
    "profile_etag": "019ced11-e4ea-7c92-90d9-8c9604f102d6"
  }
}
