{
  "event_id": "019e2616-0388-70f0-878c-fc173a50ef63",
  "occurred_at": "2026-05-14T10:43:57.448196076Z",
  "knot_id": "foolery-1722",
  "type": "knot.lease_data_set",
  "data": {
    "lease_data": {
      "agent_info": {
        "agent_name": "Codex",
        "agent_type": "cli",
        "model": "GPT",
        "model_version": "5.5",
        "provider": "Codex"
      },
      "lease_type": "agent",
      "nickname": "foolery:terminal_manager_take:term-1778755300255-788saf",
      "timeout_seconds": 600
    }
  }
}
