{
  "event_id": "019d3f4c-7888-7cb1-b62b-6c1a2a3d5239",
  "occurred_at": "2026-03-30T15:11:09.44835Z",
  "type": "idx.knot_head",
  "data": {
    "blocked_from_state": null,
    "deferred_from_state": null,
    "gate": {
      "owner_kind": "agent"
    },
    "invariants": [],
    "knot_id": "foolery-63f9",
    "profile_id": "autopilot",
    "state": "lease_terminated",
    "terminal": true,
    "title": "Lease: foolery:terminal_manager_take:term-1774883461433-b632ib",
    "type": "lease",
    "updated_at": "2026-03-30T15:11:09.44835Z",
    "workflow_id": "compatibility"
  }
}
