{
  "event_id": "019d3f39-5a31-7ea0-a9b6-b2bf4e110953",
  "occurred_at": "2026-03-30T14:50:16.497303Z",
  "type": "idx.knot_head",
  "data": {
    "blocked_from_state": null,
    "deferred_from_state": null,
    "gate": {
      "owner_kind": "agent"
    },
    "invariants": [],
    "knot_id": "foolery-0308",
    "profile_id": "autopilot",
    "state": "lease_terminated",
    "terminal": true,
    "title": "Lease: foolery:terminal_manager_take:term-1774881851760-m9b1x7",
    "type": "lease",
    "updated_at": "2026-03-30T14:50:16.497303Z",
    "workflow_id": "compatibility"
  }
}
