{
  "event_id": "019d3f09-bfb7-7f80-a62f-16925c9a7c54",
  "occurred_at": "2026-03-30T13:58:16.753474Z",
  "type": "idx.knot_head",
  "data": {
    "blocked_from_state": null,
    "deferred_from_state": null,
    "gate": {
      "owner_kind": "agent"
    },
    "invariants": [],
    "knot_id": "foolery-23f3",
    "profile_id": "autopilot",
    "state": "shipment_review",
    "terminal": false,
    "title": "Agents settings: streamline scanned-agent rows and button styling",
    "type": "work",
    "updated_at": "2026-03-30T13:58:16.753474Z",
    "workflow_id": "compatibility"
  }
}
