{
  "event_id": "019daf99-58b4-7eb1-8483-d626050fb558",
  "occurred_at": "2026-04-21T10:32:35.764312Z",
  "type": "idx.knot_head",
  "data": {
    "blocked_from_state": null,
    "deferred_from_state": null,
    "gate": {
      "owner_kind": "agent"
    },
    "invariants": [],
    "knot_id": "foolery-d7b7",
    "next_step_metadata": {
      "action_kind": "produce",
      "action_state": "planning",
      "output": {
        "access_hint": "kno show",
        "artifact_type": "remote_main"
      },
      "owner": {
        "agent_model": null,
        "agent_name": null,
        "agent_version": null,
        "kind": "agent"
      }
    },
    "profile_id": "autopilot",
    "state": "ready_for_planning",
    "step_metadata": {
      "action_kind": "produce",
      "action_state": "planning",
      "output": {
        "access_hint": "kno show",
        "artifact_type": "remote_main"
      },
      "owner": {
        "agent_model": null,
        "agent_name": null,
        "agent_version": null,
        "kind": "agent"
      }
    },
    "terminal": false,
    "title": "foolery doctor fails ENOENT on linux",
    "type": "work",
    "updated_at": "2026-04-21T10:32:35.764312Z",
    "workflow_id": "work_sdlc"
  }
}
