{
  "event_id": "019d2994-858f-75b0-b3a0-5e15778a8139",
  "occurred_at": "2026-03-26T09:58:12.623113Z",
  "type": "idx.knot_head",
  "data": {
    "deferred_from_state": null,
    "gate": {
      "owner_kind": "agent"
    },
    "invariants": [],
    "knot_id": "foolery-2031",
    "profile_id": "autopilot_with_pr",
    "state": "lease_terminated",
    "terminal": true,
    "title": "Lease: foolery:terminal_manager_take:term-1774516513413-eyqpot",
    "type": "lease",
    "updated_at": "2026-03-26T09:58:12.623113Z",
    "workflow_id": "compatibility"
  }
}
