{
  "event_id": "019db8dc-9f46-7853-b4c8-0f0116a35335",
  "occurred_at": "2026-04-23T05:42:39.686185683Z",
  "knot_id": "foolery-18b6",
  "type": "knot.note_added",
  "data": {
    "agentname": "Codex",
    "content": "Implementation plan\n\nRoot cause\n- `src/components/notification-bell.tsx` always calls `buildBeatFocusHref(...)` with the current query string, so clicks from non-list screens preserve views like `finalcut`, `history`, or `diagnostics`.\n- On those screens, setting `beat=` alone does not route the user onto a list screen, so the detail lightbox never opens.\n\nPlanned changes\n1. Add a beat-focus routing helper in `src/lib/beat-navigation.ts` (or a nearby shared helper if the file length budget requires a split) that can compute the correct `/beats` href for a known beat.\n2. Use the existing workflow utilities to classify the beat before routing: `builtinProfileDescriptor(beat.profileId ?? beat.workflowId)` + `workflowStatePhase(workflow, beat.state)`.\n3. Map queued beats to `view=queues` + `state=queued`, and active beats to `view=active` + `state=in_action`. Preserve `repo`, `detailRepo`, and unrelated search params unless they conflict with the forced target view.\n4. Keep the no-regression path: if the current screen is already the correct list view, keep the existing single-click behavior and just ensure the focused beat URL still includes the right `beat` and repo params.\n5. Update `src/components/notification-bell.tsx` so `focusBeat` becomes async: resolve repo path, fetch the beat with `fetchBeat`, compute the target href, set the active repo when available, and perform one router navigation that both lands on the right screen and opens the detail lightbox.\n6. Leave `src/components/beat-detail-lightbox.tsx` unchanged unless validation proves otherwise; the current lightbox should already respond once the route lands on the correct list screen with `beat=` present.\n\nTest strategy\n- Extend `src/lib/__tests__/beat-navigation.test.ts` with route-building cases for:\n  - non-list view -> queued beat => `/beats?...view=queues&state=queued&beat=...`\n  - non-list view -> active beat => `/beats?...view=active&state=in_action&beat=...`\n  - already-on-queues / already-on-active => still opens via `beat=` with no regression\n- Add a focused unit/component test around `src/components/notification-bell.tsx` or the extracted helper to prove the click path fetches the beat, selects the right view, and pushes the expected href.\n- Browser validation: from a non-queues/non-active route, click a notification beat ID and assert both the route change and visible beat-detail dialog.\n\nComplexity and risks\n- Complexity: low-to-medium; the change is localized but involves async click navigation and URL-state preservation.\n- Primary risk: preserving unrelated query params while force-switching views can accidentally carry stale `state`/`view` combinations. The helper should normalize those explicitly.\n- Secondary risk: notification clicks for beats in terminal or unclassifiable states. Decide explicitly whether to keep current behavior or route to a safe default, but do not silently misclassify queued vs active.\n\nHierarchy / decomposition\n- No child knots needed; this is a single-path UI fix with helper + tests.",
    "datetime": "2026-04-23T05:42:15Z",
    "entry_id": "019db8dc-9f46-7853-b4c8-0effa2776836",
    "model": "gpt",
    "username": "Codex",
    "version": "5.4"
  }
}
