{
  "event_id": "019d1624-b5cd-7600-8d04-b01912c03d6c",
  "occurred_at": "2026-03-22T15:23:17.837675Z",
  "type": "idx.knot_head",
  "data": {
    "deferred_from_state": null,
    "gate": {
      "owner_kind": "agent"
    },
    "invariants": [],
    "knot_id": "foolery-d984",
    "profile_id": "autopilot",
    "state": "ready_for_shipment",
    "terminal": false,
    "title": "Create New:  Spawn asynchronous  Scope Refinement job when ticket is created.",
    "type": "work",
    "updated_at": "2026-03-22T15:23:17.837675Z",
    "workflow_id": "compatibility"
  }
}
