{
  "event_id": "019d145d-f7e5-7b12-830c-80e37617e245",
  "occurred_at": "2026-03-22T07:06:35.87767Z",
  "type": "idx.knot_head",
  "data": {
    "deferred_from_state": null,
    "gate": {
      "owner_kind": "agent"
    },
    "invariants": [],
    "knot_id": "foolery-210a",
    "profile_id": "autopilot_with_pr",
    "state": "lease_active",
    "terminal": false,
    "title": "Lease: foolery:terminal_manager_take:term-1774162605882-ahwr5q",
    "type": "lease",
    "updated_at": "2026-03-22T07:06:35.87767Z",
    "workflow_id": "compatibility"
  }
}
