{
  "event_id": "019d1618-d1ab-7680-82df-bfd3f9b6ee4d",
  "occurred_at": "2026-03-22T15:10:18.539792Z",
  "type": "idx.knot_head",
  "data": {
    "deferred_from_state": null,
    "gate": {
      "owner_kind": "agent"
    },
    "invariants": [],
    "knot_id": "foolery-d984",
    "profile_id": "autopilot",
    "state": "shipment",
    "terminal": false,
    "title": "Create New:  Spawn asynchronous  Scope Refinement job when ticket is created.",
    "type": "work",
    "updated_at": "2026-03-22T15:10:18.539792Z",
    "workflow_id": "compatibility"
  },
  "precondition": {
    "profile_etag": "019d1618-9e31-7c83-8032-e04a4fe71e8c"
  }
}
