{
  "event_id": "019d109a-084b-7523-96d0-d7736bcfc481",
  "occurred_at": "2026-03-21T13:33:43.371162Z",
  "type": "idx.knot_head",
  "data": {
    "deferred_from_state": null,
    "gate": {
      "owner_kind": "agent"
    },
    "invariants": [],
    "knot_id": "foolery-16a0",
    "profile_id": "autopilot_with_pr",
    "state": "lease_active",
    "terminal": false,
    "title": "Lease: foolery:terminal_manager_take:term-1774099543559-52g3nl",
    "type": "lease",
    "updated_at": "2026-03-21T13:33:43.371162Z",
    "workflow_id": "compatibility"
  }
}
