{
  "event_id": "019d10a0-1a3c-71e1-9033-13ba2af86e1b",
  "occurred_at": "2026-03-21T13:40:21.1801Z",
  "type": "idx.knot_head",
  "data": {
    "deferred_from_state": null,
    "gate": {
      "owner_kind": "agent"
    },
    "invariants": [],
    "knot_id": "foolery-802e",
    "profile_id": "autopilot_with_pr",
    "state": "lease_active",
    "terminal": false,
    "title": "Lease: foolery:terminal_manager_take:term-1774099543559-52g3nl",
    "type": "lease",
    "updated_at": "2026-03-21T13:40:21.1801Z",
    "workflow_id": "compatibility"
  }
}
