{
  "event_id": "019d0f79-be4a-77e1-830a-c2c233be44f7",
  "occurred_at": "2026-03-21T08:18:50.058875Z",
  "type": "idx.knot_head",
  "data": {
    "deferred_from_state": null,
    "gate": {
      "owner_kind": "agent"
    },
    "invariants": [],
    "knot_id": "foolery-634b",
    "profile_id": "autopilot_with_pr",
    "state": "lease_terminated",
    "terminal": true,
    "title": "Lease: foolery:terminal_manager_take:term-1774080624956-q3ar3y",
    "type": "lease",
    "updated_at": "2026-03-21T08:18:50.058875Z",
    "workflow_id": "compatibility"
  }
}
