{
  "event_id": "019d7bbb-a739-7081-b3a9-6c8f15f584a7",
  "occurred_at": "2026-04-11T08:49:48.857061Z",
  "type": "idx.knot_head",
  "data": {
    "blocked_from_state": null,
    "deferred_from_state": null,
    "gate": {
      "owner_kind": "agent"
    },
    "invariants": [],
    "knot_id": "foolery-2dfe",
    "next_step_metadata": {
      "action_kind": "produce",
      "action_state": "planning",
      "output": {
        "access_hint": "kno show",
        "artifact_type": "remote_main"
      },
      "owner": {
        "agent_model": null,
        "agent_name": null,
        "agent_version": null,
        "kind": "agent"
      }
    },
    "profile_id": "autopilot",
    "state": "ready_for_planning",
    "step_metadata": {
      "action_kind": "produce",
      "action_state": "planning",
      "output": {
        "access_hint": "kno show",
        "artifact_type": "remote_main"
      },
      "owner": {
        "agent_model": null,
        "agent_name": null,
        "agent_version": null,
        "kind": "agent"
      }
    },
    "terminal": false,
    "title": "Add search/filter capability to OpenCode CLI model selection",
    "type": "work",
    "updated_at": "2026-04-11T08:49:48.857061Z",
    "workflow_id": "work_sdlc"
  }
}
