{
  "event_id": "019d1a2f-316b-7141-9b6c-981cb9953034",
  "occurred_at": "2026-03-23T10:13:13.700369Z",
  "type": "idx.knot_head",
  "data": {
    "deferred_from_state": null,
    "gate": {
      "owner_kind": "agent"
    },
    "invariants": [],
    "knot_id": "foolery-d8cb",
    "profile_id": "autopilot",
    "state": "shipment",
    "terminal": false,
    "title": "Audit Page loaded with mistakes",
    "type": "work",
    "updated_at": "2026-03-23T10:13:13.700369Z",
    "workflow_id": "compatibility"
  }
}
