{
  "event_id": "019d19df-78d6-7903-969d-ae346547cc35",
  "occurred_at": "2026-03-23T08:46:09.110405Z",
  "type": "idx.knot_head",
  "data": {
    "deferred_from_state": null,
    "gate": {
      "owner_kind": "agent"
    },
    "invariants": [],
    "knot_id": "foolery-03f4",
    "profile_id": "autopilot_with_pr",
    "state": "lease_active",
    "terminal": false,
    "title": "Lease: foolery:terminal_manager_take:term-1774255557669-o1luhx",
    "type": "lease",
    "updated_at": "2026-03-23T08:46:09.110405Z",
    "workflow_id": "compatibility"
  }
}
