{
  "event_id": "019d1a24-67a2-7ec2-91e7-bb240e352f3e",
  "occurred_at": "2026-03-23T10:01:26.683816Z",
  "type": "idx.knot_head",
  "data": {
    "deferred_from_state": null,
    "gate": {
      "owner_kind": "agent"
    },
    "invariants": [],
    "knot_id": "foolery-d8cb",
    "profile_id": "autopilot",
    "state": "planning",
    "terminal": false,
    "title": "Audit Page loaded with mistakes",
    "type": "work",
    "updated_at": "2026-03-23T10:01:26.683816Z",
    "workflow_id": "compatibility"
  }
}
