{
  "event_id": "019df258-5017-7ef3-8d80-07b8ea9c6005",
  "occurred_at": "2026-05-04T09:36:07.191605Z",
  "type": "idx.knot_head",
  "data": {
    "blocked_from_state": null,
    "deferred_from_state": null,
    "gate": {
      "owner_kind": "agent"
    },
    "invariants": [],
    "knot_id": "foolery-4f53",
    "next_step_metadata": {
      "action_kind": "produce",
      "action_state": "lease_active",
      "output": {
        "artifact_type": ""
      },
      "owner": {
        "agent_model": null,
        "agent_name": null,
        "agent_version": null,
        "kind": "agent"
      }
    },
    "profile_id": "lease",
    "state": "lease_ready",
    "step_metadata": {
      "action_kind": "produce",
      "action_state": "lease_active",
      "output": {
        "artifact_type": ""
      },
      "owner": {
        "agent_model": null,
        "agent_name": null,
        "agent_version": null,
        "kind": "agent"
      }
    },
    "terminal": false,
    "title": "Lease: claim-foolery-b47c",
    "type": "lease",
    "updated_at": "2026-05-04T09:36:07.191605Z",
    "workflow_id": "lease_sdlc"
  }
}
