{
  "event_id": "019df258-8a55-7250-9e14-7aa315425316",
  "occurred_at": "2026-05-04T09:36:22.101004Z",
  "type": "idx.knot_head",
  "data": {
    "blocked_from_state": null,
    "deferred_from_state": null,
    "gate": {
      "owner_kind": "agent"
    },
    "invariants": [],
    "knot_id": "foolery-4f53",
    "profile_id": "lease",
    "state": "lease_terminated",
    "terminal": true,
    "title": "Lease: claim-foolery-b47c",
    "type": "lease",
    "updated_at": "2026-05-04T09:36:22.101004Z",
    "workflow_id": "lease_sdlc"
  }
}
