{
  "event_id": "019df277-9215-7282-ad76-8f854c9b6ed0",
  "occurred_at": "2026-05-04T10:10:15.701985Z",
  "type": "idx.knot_head",
  "data": {
    "blocked_from_state": null,
    "deferred_from_state": null,
    "gate": {
      "owner_kind": "agent"
    },
    "invariants": [],
    "knot_id": "foolery-9a05",
    "next_step_metadata": {
      "action_kind": "produce",
      "action_state": "implementation",
      "output": {
        "artifact_type": "remote_main"
      },
      "owner": {
        "agent_model": null,
        "agent_name": null,
        "agent_version": null,
        "kind": "agent"
      }
    },
    "profile_id": "autopilot",
    "state": "ready_for_implementation",
    "step_metadata": {
      "action_kind": "produce",
      "action_state": "implementation",
      "output": {
        "artifact_type": "remote_main"
      },
      "owner": {
        "agent_model": null,
        "agent_name": null,
        "agent_version": null,
        "kind": "agent"
      }
    },
    "terminal": false,
    "title": "Refine overview lease actions",
    "type": "work",
    "updated_at": "2026-05-04T10:10:15.701985Z",
    "workflow_id": "work_sdlc"
  }
}
