{
  "event_id": "019d5493-3f3d-7b72-9551-f34b6b0a2191",
  "occurred_at": "2026-04-03T18:20:29.373635Z",
  "type": "idx.knot_head",
  "data": {
    "blocked_from_state": null,
    "deferred_from_state": null,
    "gate": {
      "owner_kind": "agent"
    },
    "invariants": [],
    "knot_id": "foolery-c198",
    "next_step_metadata": {
      "action_kind": "gate",
      "action_state": "shipment_review",
      "output": {
        "artifact_type": "remote_main"
      },
      "owner": {
        "agent_model": null,
        "agent_name": null,
        "agent_version": null,
        "kind": "agent"
      }
    },
    "profile_id": "autopilot",
    "state": "ready_for_shipment_review",
    "step_metadata": {
      "action_kind": "gate",
      "action_state": "shipment_review",
      "output": {
        "artifact_type": "remote_main"
      },
      "owner": {
        "agent_model": null,
        "agent_name": null,
        "agent_version": null,
        "kind": "agent"
      }
    },
    "terminal": false,
    "title": "Add interactive Copilot session support",
    "type": "work",
    "updated_at": "2026-04-03T18:20:29.373635Z",
    "workflow_id": "compatibility"
  }
}
